abstract_singleton/__init__.py
abstract_singleton-1.0.1.dist-info/METADATA
abstract_singleton-1.0.1.dist-info/WHEEL
abstract_singleton-1.0.1.dist-info/licenses/LICENSE
abstract_singleton-1.0.1.dist-info/RECORD
